twitch_monitor_discord_bot/__init__.py
twitch_monitor_discord_bot/__main__.py
twitch_monitor_discord_bot/command_processor.py
twitch_monitor_discord_bot/config.py
twitch_monitor_discord_bot/discord_bot.py
twitch_monitor_discord_bot/jokes.py
twitch_monitor_discord_bot/quotedb.json
twitch_monitor_discord_bot/quotes.py
twitch_monitor_discord_bot/twitch_monitor.py
twitch_monitor_discord_bot/utils.py
twitch_monitor_discord_bot-2.0.0.dist-info/LICENSE
twitch_monitor_discord_bot-2.0.0.dist-info/METADATA
twitch_monitor_discord_bot-2.0.0.dist-info/WHEEL
twitch_monitor_discord_bot-2.0.0.dist-info/top_level.txt
twitch_monitor_discord_bot-2.0.0.dist-info/RECORD
