Metadata-Version: 2.1
Name: twitch-monitor-discord-bot
Version: 2.0.0
Summary: A discord bot for monitoring twitch streams
Home-page: http://github.com/eriknyquist/twitch_monitor_discord_bot
Author: Erik Nyquist
Author-email: eknyquist@gmail.com
License: Apache 2.0
Platform: UNKNOWN
Requires-Dist: requests
Requires-Dist: twitch-python
Requires-Dist: versionedobj (>=2.0.0)
Requires-Dist: discord.py (==1.7.3)
Requires-Dist: discord (==1.7.3)
Requires-Dist: nltk
